nonebot_plugin_face2cartoonpic/__init__.py
nonebot_plugin_face2cartoonpic/config.py
nonebot_plugin_face2cartoonpic/limiter.py
nonebot_plugin_face2cartoonpic/tencentapi.py
nonebot_plugin_face2cartoonpic-0.0.5.dist-info/LICENSE
nonebot_plugin_face2cartoonpic-0.0.5.dist-info/METADATA
nonebot_plugin_face2cartoonpic-0.0.5.dist-info/WHEEL
nonebot_plugin_face2cartoonpic-0.0.5.dist-info/top_level.txt
nonebot_plugin_face2cartoonpic-0.0.5.dist-info/RECORD
