Metadata-Version: 2.1
Name: nonebot-plugin-face2cartoonpic
Version: 0.0.5
Summary: 基于 腾讯云合成图的 以图绘图 NoneBot2插件
Home-page: https://github.com/ANGJustinl/nonebot_plugin_face2cartoonpic
Author: ANGJustinl
Author-email: angjustin@163.com
Keywords: pip,nonebot2,nonebot,nonebot_plugin
Platform: any
Classifier: Programming Language :: Python :: 3
Classifier: Operating System :: OS Independent
Requires-Python: >=3.8
License-File: LICENSE
Requires-Dist: nb-cli (>=0.6.7pydantic>=1.9.2)
